SeismicFold/Bin.py
SeismicFold/Fold.py
SeismicFold/Grid.py
SeismicFold/__init__.py
SeismicFold/helpers.py
SeismicFold-0.1.0.dist-info/LICENSE
SeismicFold-0.1.0.dist-info/METADATA
SeismicFold-0.1.0.dist-info/WHEEL
SeismicFold-0.1.0.dist-info/top_level.txt
SeismicFold-0.1.0.dist-info/RECORD
